Metadata-Version: 2.1
Name: PyBetterFileIO
Version: 1.0.9
Summary: A faster, more efficient Python file input and output framework
Home-page: https://github.com/keithhb33/PyBetterFileIO
Download-URL: https://github.com/keithhb33/PyBetterFileIO/archive/refs/tags/v1.0.9.tar.gz
Author: Keith Burroughs
Author-email: keithburroughs33@gmail.com
License: NCSA
Keywords: python,files,file,folder,folders,input,output,fileio,file management,script
Classifier: Development Status :: 3 - Alpha
Classifier: Intended Audience :: Developers
Classifier: Topic :: Software Development :: Build Tools
Classifier: License :: OSI Approved :: MIT License
Classifier: Programming Language :: Python :: 3
Classifier: Programming Language :: Python :: 3.4
Classifier: Programming Language :: Python :: 3.5
Classifier: Programming Language :: Python :: 3.6
Classifier: Programming Language :: Python :: 3.7
Classifier: Programming Language :: Python :: 3.8
Classifier: Programming Language :: Python :: 3.9
Classifier: Programming Language :: Python :: 3.10
Classifier: Programming Language :: Python :: 3.11
License-File: LICENSE.txt
